sentiment_analysis_csci_e89/__init__.py
sentiment_analysis_csci_e89/data_cleaning.py
sentiment_analysis_csci_e89/modeling.py
sentiment_analysis_csci_e89/pre_processing.py
sentiment_analysis_csci_e89/predict_newdata.py
sentiment_analysis_csci_e89/pretrained_embeddings.py
sentiment_analysis_csci_e89-2.1.1.dist-info/LICENSE.txt
sentiment_analysis_csci_e89-2.1.1.dist-info/METADATA
sentiment_analysis_csci_e89-2.1.1.dist-info/WHEEL
sentiment_analysis_csci_e89-2.1.1.dist-info/top_level.txt
sentiment_analysis_csci_e89-2.1.1.dist-info/RECORD
