Metadata-Version: 2.1
Name: sentiment-analysis-csci-e89
Version: 2.1.1
Summary: Package for end to end setiment analysis using Neural Architectures
Home-page: https://github.com/stefano10p/-sentiment_analysis_csci_e89-
Author: Stefano Parravano
Author-email: stefanoparravano10@gmail.com
License: MIT
Platform: UNKNOWN
Classifier: Development Status :: 3 - Alpha
Classifier: Intended Audience :: Developers
Classifier: License :: OSI Approved :: BSD License
Classifier: Natural Language :: English
Classifier: Operating System :: POSIX :: Linux
Classifier: Programming Language :: Python :: 3.6
Classifier: Programming Language :: Python :: 3.7
Classifier: Programming Language :: Python :: 3.8
Classifier: Programming Language :: Python :: 3.4
Classifier: Programming Language :: Python :: Implementation
Requires-Dist: pandas
Requires-Dist: numpy (>=1.16)
Requires-Dist: keras (==2.3.1)
Requires-Dist: pandas-confusion (==0.0.6)
Requires-Dist: pandas-ml (==0.6.1)
Requires-Dist: tensorflow (==2.0.1)
Requires-Dist: tensorflow-estimator (==2.0.1)
Requires-Dist: setuptools (>=41.0.0)
